setup.py
exam_distributions/Binomialdistribution.py
exam_distributions/Gaussiandistribution.py
exam_distributions/Generaldistribution.py
exam_distributions/__init__.py
exam_distributions.egg-info/PKG-INFO
exam_distributions.egg-info/SOURCES.txt
exam_distributions.egg-info/dependency_links.txt
exam_distributions.egg-info/not-zip-safe
exam_distributions.egg-info/top_level.txt