Metadata-Version: 1.0
Name: exam-distributions
Version: 0.1
Summary: example distributions
Home-page: UNKNOWN
Author: UNKNOWN
Author-email: UNKNOWN
License: UNKNOWN
Platform: UNKNOWN
